<INDIVIDUAL>
<ID>subject6580</ID>
<WRITING>
	<TITLE>   </TITLE>
	<DATE> 2017-04-27 18:06:24 </DATE>
	<INFO> reddit post </INFO>
	<TEXT> "I *told* you, I don't know whose fuckin' woods these are! *Jesus!!!*" </TEXT>
</WRITING>
<WRITING>
	<TITLE>   </TITLE>
	<DATE> 2017-04-27 18:00:50 </DATE>
	<INFO> reddit post </INFO>
	<TEXT> Given enough time, they would have eventually reached a similar level.  </TEXT>
</WRITING>
<WRITING>
	<TITLE>   </TITLE>
	<DATE> 2017-04-27 17:57:39 </DATE>
	<INFO> reddit post </INFO>
	<TEXT> What? </TEXT>
</WRITING>
<WRITING>
	<TITLE>   </TITLE>
	<DATE> 2017-04-27 17:55:10 </DATE>
	<INFO> reddit post </INFO>
	<TEXT> Councilman Tom Boyer, Appleton, Wisconsin.  </TEXT>
</WRITING>
<WRITING>
	<TITLE>   </TITLE>
	<DATE> 2017-04-27 17:54:10 </DATE>
	<INFO> reddit post </INFO>
	<TEXT> Who says they aren't? </TEXT>
</WRITING>
<WRITING>
	<TITLE>   </TITLE>
	<DATE> 2017-04-27 17:47:22 </DATE>
	<INFO> reddit post </INFO>
	<TEXT> Imagine all the sick, crazy shit the was decided on that throne. Or maybe he just read his horoscope there. Thanks to all the men and women in Bates with their ARs. </TEXT>
</WRITING>
<WRITING>
	<TITLE>   </TITLE>
	<DATE> 2017-04-27 17:39:48 </DATE>
	<INFO> reddit post </INFO>
	<TEXT> We had the aforementioned 27'' in our basement rec-room, which was pretty big and everyone was in *awe* of it. Now, I have a 40'' in our tiny den, and everyone who comes over is like "you need a bigger set, bro." </TEXT>
</WRITING>
<WRITING>
	<TITLE>   </TITLE>
	<DATE> 2017-04-27 17:34:04 </DATE>
	<INFO> reddit post </INFO>
	<TEXT> This guy gets a bad rap as a person. He's a douche, but the kinda douche you'd like to have a beer with. As a chef, well... </TEXT>
</WRITING>
<WRITING>
	<TITLE>   </TITLE>
	<DATE> 2017-04-27 17:16:41 </DATE>
	<INFO> reddit post </INFO>
	<TEXT> I was hoping for Paranoid Antroid.  </TEXT>
</WRITING>
<WRITING>
	<TITLE> 27'' TVs seemed HUGE as a kid. </TITLE>
	<DATE> 2017-04-27 17:04:38 </DATE>
	<INFO> reddit post </INFO>
	<TEXT>  </TEXT>
</WRITING>
<WRITING>
	<TITLE>   </TITLE>
	<DATE> 2017-04-27 16:44:50 </DATE>
	<INFO> reddit post </INFO>
	<TEXT> The first recorded bro.  </TEXT>
</WRITING>
<WRITING>
	<TITLE>   </TITLE>
	<DATE> 2017-04-27 16:42:24 </DATE>
	<INFO> reddit post </INFO>
	<TEXT> My father buying a 12 pack instead of a 6 pack nine months before I was born.  </TEXT>
</WRITING>
<WRITING>
	<TITLE>   </TITLE>
	<DATE> 2017-04-27 06:49:24 </DATE>
	<INFO> reddit post </INFO>
	<TEXT> Just another meta joke circling the drain.  </TEXT>
</WRITING>
<WRITING>
	<TITLE>   </TITLE>
	<DATE> 2017-04-27 06:36:37 </DATE>
	<INFO> reddit post </INFO>
	<TEXT> He may have a simple central nervous system, but this is touching.  </TEXT>
</WRITING>
<WRITING>
	<TITLE> Reading someone's cruel reply can sometimes sting a bit, until you see that their posts consist of comments about Minecraft and the Poconos. </TITLE>
	<DATE> 2017-04-27 06:14:42 </DATE>
	<INFO> reddit post </INFO>
	<TEXT>  </TEXT>
</WRITING>
<WRITING>
	<TITLE>   </TITLE>
	<DATE> 2017-04-27 06:10:07 </DATE>
	<INFO> reddit post </INFO>
	<TEXT> ***Child Of The '80s Alert*** </TEXT>
</WRITING>
<WRITING>
	<TITLE>   </TITLE>
	<DATE> 2017-04-27 02:37:48 </DATE>
	<INFO> reddit post </INFO>
	<TEXT> That there's a benevolent god. </TEXT>
</WRITING>
<WRITING>
	<TITLE>   </TITLE>
	<DATE> 2017-04-27 02:01:41 </DATE>
	<INFO> reddit post </INFO>
	<TEXT> Nowadays, nobody will be able to watch Star Wars.

*Much* simpler. </TEXT>
</WRITING>
<WRITING>
	<TITLE> Well played Grandma, well played </TITLE>
	<DATE> 2017-04-27 01:40:02 </DATE>
	<INFO> reddit post </INFO>
	<TEXT>  </TEXT>
</WRITING>
<WRITING>
	<TITLE>   </TITLE>
	<DATE> 2017-04-27 00:07:12 </DATE>
	<INFO> reddit post </INFO>
	<TEXT> Are you gonna cum soon? </TEXT>
</WRITING>
<WRITING>
	<TITLE>   </TITLE>
	<DATE> 2017-04-26 21:08:20 </DATE>
	<INFO> reddit post </INFO>
	<TEXT> I don't know what to tell you, bro.  </TEXT>
</WRITING>
<WRITING>
	<TITLE>   </TITLE>
	<DATE> 2017-04-26 21:05:26 </DATE>
	<INFO> reddit post </INFO>
	<TEXT> Did your dad use it to bang your mother? Since I''ve tasted her sweet ladybusiness, this wouldn't be too bad. $25 </TEXT>
</WRITING>
<WRITING>
	<TITLE>   </TITLE>
	<DATE> 2017-04-26 21:02:05 </DATE>
	<INFO> reddit post </INFO>
	<TEXT> By themselves, yes, they're quite tasteless. But they're a blank canvas to which you can add any untold number of other flavors. </TEXT>
</WRITING>
<WRITING>
	<TITLE>   </TITLE>
	<DATE> 2017-04-26 18:37:38 </DATE>
	<INFO> reddit post </INFO>
	<TEXT> Comma placement confirms it's King.  </TEXT>
</WRITING>
<WRITING>
	<TITLE>   </TITLE>
	<DATE> 2017-04-26 18:36:45 </DATE>
	<INFO> reddit post </INFO>
	<TEXT> The outcry from this photo today would've been immense.  </TEXT>
</WRITING>
<WRITING>
	<TITLE>   </TITLE>
	<DATE> 2017-04-26 18:35:49 </DATE>
	<INFO> reddit post </INFO>
	<TEXT> Every girl's crazy for a sharp dressed man.  </TEXT>
</WRITING>
<WRITING>
	<TITLE>   </TITLE>
	<DATE> 2017-04-26 18:25:53 </DATE>
	<INFO> reddit post </INFO>
	<TEXT> My wife's sister came over, and then, not three minutes later the fuckin' *pizza* guys shows up and... heh...

...yeah, total let down.  </TEXT>
</WRITING>
<WRITING>
	<TITLE>   </TITLE>
	<DATE> 2017-04-26 18:23:53 </DATE>
	<INFO> reddit post </INFO>
	<TEXT> If there isn't some sort of buttery pastry product, I'm outta there.  </TEXT>
</WRITING>
<WRITING>
	<TITLE>   </TITLE>
	<DATE> 2017-04-26 17:44:54 </DATE>
	<INFO> reddit post </INFO>
	<TEXT> What did the ore boat's crew say when you got there?  </TEXT>
</WRITING>
<WRITING>
	<TITLE>   </TITLE>
	<DATE> 2017-04-26 17:36:31 </DATE>
	<INFO> reddit post </INFO>
	<TEXT> Mass hysteria.  </TEXT>
</WRITING>
<WRITING>
	<TITLE>   </TITLE>
	<DATE> 2017-04-26 17:35:12 </DATE>
	<INFO> reddit post </INFO>
	<TEXT> Fundamental Apple Cinnamonism.  </TEXT>
</WRITING>
<WRITING>
	<TITLE> ELI5: Why does prolonging sex and holding off on your climax make it feel that much better when it... comes? </TITLE>
	<DATE> 2017-04-26 16:57:22 </DATE>
	<INFO> reddit post </INFO>
	<TEXT>  </TEXT>
</WRITING>
<WRITING>
	<TITLE>   </TITLE>
	<DATE> 2017-04-26 16:31:22 </DATE>
	<INFO> reddit post </INFO>
	<TEXT> Oops, my mistake.  </TEXT>
</WRITING>
<WRITING>
	<TITLE>   </TITLE>
	<DATE> 2017-04-26 16:20:43 </DATE>
	<INFO> reddit post </INFO>
	<TEXT> Agreed. The outfit coupled with her facial expressions make this pure gold. 

Edit: thought it was an exceptionally cute boy :/ </TEXT>
</WRITING>
<WRITING>
	<TITLE>   </TITLE>
	<DATE> 2017-04-26 16:14:57 </DATE>
	<INFO> reddit post </INFO>
	<TEXT> This kid's a hero.  </TEXT>
</WRITING>
<WRITING>
	<TITLE>   </TITLE>
	<DATE> 2017-04-26 16:11:56 </DATE>
	<INFO> reddit post </INFO>
	<TEXT> You could say he was surgical.  </TEXT>
</WRITING>
<WRITING>
	<TITLE>   </TITLE>
	<DATE> 2017-04-26 15:49:12 </DATE>
	<INFO> reddit post </INFO>
	<TEXT> Some dude was slagging off the durability of Thorogood Heritage moc toes, and I was all like "Not on my watch, *bud*!"  </TEXT>
</WRITING>
<WRITING>
	<TITLE>   </TITLE>
	<DATE> 2017-04-26 15:46:00 </DATE>
	<INFO> reddit post </INFO>
	<TEXT> Apple Cinnamonatarian.  </TEXT>
</WRITING>
<WRITING>
	<TITLE>   </TITLE>
	<DATE> 2017-04-26 15:45:01 </DATE>
	<INFO> reddit post </INFO>
	<TEXT> That the price of Ramen has skyrocketed.  </TEXT>
</WRITING>
<WRITING>
	<TITLE>   </TITLE>
	<DATE> 2017-04-26 15:43:52 </DATE>
	<INFO> reddit post </INFO>
	<TEXT> Thank you for the opportunity and I wish you all the best. Cheers.  </TEXT>
</WRITING>
<WRITING>
	<TITLE>   </TITLE>
	<DATE> 2017-04-26 15:35:04 </DATE>
	<INFO> reddit post </INFO>
	<TEXT> When he described in detail being bayoneted by a Japanese soldier on Guadalcanal after I saw his scar. Turns out he had his appendix out.  </TEXT>
</WRITING>
<WRITING>
	<TITLE> That uncomfortable feeling you got as a kid when you heard your parents having sex eventually morphs into that uncomfortable feeling you get when you know your kids heard you having sex. </TITLE>
	<DATE> 2017-04-26 05:25:04 </DATE>
	<INFO> reddit post </INFO>
	<TEXT>  </TEXT>
</WRITING>
<WRITING>
	<TITLE>   </TITLE>
	<DATE> 2017-04-26 04:19:44 </DATE>
	<INFO> reddit post </INFO>
	<TEXT> You can't wash under your ballbag too much. </TEXT>
</WRITING>
<WRITING>
	<TITLE> The guys who programmed the music for NES games must have been listening to a TON of Iron Maiden. </TITLE>
	<DATE> 2017-04-26 03:24:37 </DATE>
	<INFO> reddit post </INFO>
	<TEXT>  </TEXT>
</WRITING>
<WRITING>
	<TITLE>   </TITLE>
	<DATE> 2017-04-26 03:11:05 </DATE>
	<INFO> reddit post </INFO>
	<TEXT> "That kid... is on the escalator again." I hear ya. 

Edit: kiss me, baby </TEXT>
</WRITING>
<WRITING>
	<TITLE>   </TITLE>
	<DATE> 2017-04-26 03:03:27 </DATE>
	<INFO> reddit post </INFO>
	<TEXT> That's a Texas-sized ten-four. </TEXT>
</WRITING>
<WRITING>
	<TITLE>   </TITLE>
	<DATE> 2017-04-26 01:10:42 </DATE>
	<INFO> reddit post </INFO>
	<TEXT> Ah, touch. </TEXT>
</WRITING>
<WRITING>
	<TITLE>   </TITLE>
	<DATE> 2017-04-26 01:03:55 </DATE>
	<INFO> reddit post </INFO>
	<TEXT> That is correct. Showroom Dummies, I believe. </TEXT>
</WRITING>
<WRITING>
	<TITLE>   </TITLE>
	<DATE> 2017-04-26 00:07:45 </DATE>
	<INFO> reddit post </INFO>
	<TEXT> True, but I'd take the traditional approach and Nerf the trouble areas first. </TEXT>
</WRITING>
<WRITING>
	<TITLE>   </TITLE>
	<DATE> 2017-04-26 00:04:00 </DATE>
	<INFO> reddit post </INFO>
	<TEXT> I also shop for mustache wax and $300 flannel shirts. </TEXT>
</WRITING>
<WRITING>
	<TITLE>   </TITLE>
	<DATE> 2017-04-25 23:47:12 </DATE>
	<INFO> reddit post </INFO>
	<TEXT> Maybe just Nerf fundamentalist Muslims? </TEXT>
</WRITING>
<WRITING>
	<TITLE>   </TITLE>
	<DATE> 2017-04-25 23:44:52 </DATE>
	<INFO> reddit post </INFO>
	<TEXT> Reading Amazon boot reviews. </TEXT>
</WRITING>
<WRITING>
	<TITLE>   </TITLE>
	<DATE> 2017-04-25 23:44:20 </DATE>
	<INFO> reddit post </INFO>
	<TEXT> $3400 for 10 MB? Seems reasonable.  </TEXT>
</WRITING>
<WRITING>
	<TITLE>   </TITLE>
	<DATE> 2017-04-25 23:33:20 </DATE>
	<INFO> reddit post </INFO>
	<TEXT> That's too sexy, bro. </TEXT>
</WRITING>
<WRITING>
	<TITLE>   </TITLE>
	<DATE> 2017-04-25 23:26:58 </DATE>
	<INFO> reddit post </INFO>
	<TEXT> When I fell asleep southbound on the Red Line and ended up at the 95th street station.  </TEXT>
</WRITING>
<WRITING>
	<TITLE>   </TITLE>
	<DATE> 2017-04-25 22:02:21 </DATE>
	<INFO> reddit post </INFO>
	<TEXT> Tell him to *not* put her in his bike basket.  </TEXT>
</WRITING>
<WRITING>
	<TITLE>   </TITLE>
	<DATE> 2017-04-25 21:52:50 </DATE>
	<INFO> reddit post </INFO>
	<TEXT> I was *super* hungover.  </TEXT>
</WRITING>
<WRITING>
	<TITLE>   </TITLE>
	<DATE> 2017-04-25 21:50:14 </DATE>
	<INFO> reddit post </INFO>
	<TEXT> Yeah, that'd be pretty fucked up.  </TEXT>
</WRITING>
<WRITING>
	<TITLE>   </TITLE>
	<DATE> 2017-04-25 21:48:21 </DATE>
	<INFO> reddit post </INFO>
	<TEXT> I know this sounds crazy, but could you, like, ask your dad?  </TEXT>
</WRITING>
<WRITING>
	<TITLE> I've fathered two boys and am responsible for their upbringing and future, but the big brother part of me still wants to trip them and repeat everything they say in a mocking tone. </TITLE>
	<DATE> 2017-04-25 21:43:01 </DATE>
	<INFO> reddit post </INFO>
	<TEXT>  </TEXT>
</WRITING>
<WRITING>
	<TITLE>   </TITLE>
	<DATE> 2017-04-25 21:30:56 </DATE>
	<INFO> reddit post </INFO>
	<TEXT> Do you know if she's wild in bed? She looks like she'd be wild in bed.  </TEXT>
</WRITING>
<WRITING>
	<TITLE>   </TITLE>
	<DATE> 2017-04-25 21:30:11 </DATE>
	<INFO> reddit post </INFO>
	<TEXT> That's brutal, dude.  </TEXT>
</WRITING>
<WRITING>
	<TITLE>   </TITLE>
	<DATE> 2017-04-25 20:22:02 </DATE>
	<INFO> reddit post </INFO>
	<TEXT> I hate to be so ineloquent and crass regarding an article about Oxford, but this is a dump truck full of bullshit.  </TEXT>
</WRITING>
<WRITING>
	<TITLE>   </TITLE>
	<DATE> 2017-04-25 20:07:29 </DATE>
	<INFO> reddit post </INFO>
	<TEXT> If you're by yourself, make sure to close your mouth. If you're with a partner, you can't come quick enough.  </TEXT>
</WRITING>
<WRITING>
	<TITLE>   </TITLE>
	<DATE> 2017-04-25 20:02:37 </DATE>
	<INFO> reddit post </INFO>
	<TEXT> Big-dicked studs pounding petite teens.  </TEXT>
</WRITING>
</INDIVIDUAL>
